smartsquash/__init__.py
smartsquash/__main__.py
smartsquash/decorators.py
smartsquash/fixup.py
smartsquash/helpers.py
smartsquash/sq.py
smartsquash/squash.py
smartsquash-0.2.1.dist-info/entry_points.txt
smartsquash-0.2.1.dist-info/LICENSE
smartsquash-0.2.1.dist-info/WHEEL
smartsquash-0.2.1.dist-info/METADATA
smartsquash-0.2.1.dist-info/RECORD
