Metadata-Version: 2.1
Name: smartsquash
Version: 0.2.1
Summary: Makes daily git workflows easier, automates rebases or fixups.
Home-page: https://github.com/max-wittig/smartsquash
License: MIT
Keywords: git,developers,squash,rebase
Author: Max Wittig
Author-email: max.wittig95@gmail.com
Requires-Python: >=3.8,<4.0
Classifier: Development Status :: 2 - Pre-Alpha
Classifier: Environment :: Console
Classifier: Intended Audience :: Developers
Classifier: License :: OSI Approved :: MIT License
Classifier: Operating System :: OS Independent
Classifier: Programming Language :: Python :: 3
Classifier: Programming Language :: Python :: 3.8
Classifier: Topic :: Software Development
Classifier: Topic :: Utilities
Requires-Dist: gitpython (>=3.0.5,<4.0.0)
Requires-Dist: loguru (>=0.4.1,<0.5.0)
Project-URL: Repository, https://github.com/max-wittig/smartsquash
